nhl_core/__init__.py
nhl_core/contents.py
nhl_core/endpoints.py
nhl_core-0.0.0.dist-info/LICENSE
nhl_core-0.0.0.dist-info/METADATA
nhl_core-0.0.0.dist-info/WHEEL
nhl_core-0.0.0.dist-info/top_level.txt
nhl_core-0.0.0.dist-info/RECORD
