Metadata-Version: 2.1
Name: nhl-core
Version: 0.0.0
Summary: A package to pull NHL historical data, and create the objects to hold the data.
Author-email: Brent Barbachem <barbacbd@gmail.com>
License: MIT
Keywords: python,python3,sports,hockey,nhl
Classifier: Intended Audience :: Science/Research
Classifier: License :: Freeware
Classifier: Natural Language :: English
Classifier: Operating System :: MacOS :: MacOS X
Classifier: Operating System :: POSIX :: Linux
Classifier: Operating System :: Microsoft :: Windows
Classifier: Programming Language :: Python :: 3
Classifier: Topic :: Software Development
Requires-Python: >=3.7
License-File: LICENSE
Requires-Dist: requests
Provides-Extra: tests
Requires-Dist: pytest ; extra == 'tests'
Requires-Dist: coverage ; extra == 'tests'
Requires-Dist: pytest-cov ; extra == 'tests'
